{
  "$schema": "https://json-schema.org/draft/2020-12/schema",
  "properties": {
    "colorSchemeJson": {
      "type": [
        "null",
        "string"
      ]
    },
    "colors": {
      "items": {
        "type": "string"
      },
      "type": [
        "array",
        "null"
      ]
    },
    "elementCount": {
      "format": "int32",
      "type": [
        "integer",
        "null"
      ]
    },
    "fabricJson": {
      "type": [
        "null",
        "string"
      ]
    },
    "height": {
      "format": "int32",
      "type": [
        "integer",
        "null"
      ]
    },
    "iconCategory": {
      "type": [
        "null",
        "string"
      ]
    },
    "iconStyle": {
      "type": [
        "null",
        "string"
      ]
    },
    "imageCategory": {
      "type": [
        "null",
        "string"
      ]
    },
    "layoutCategory": {
      "type": [
        "null",
        "string"
      ]
    },
    "materialId": {
      "type": "string"
    },
    "mood": {
      "type": [
        "null",
        "string"
      ]
    },
    "preview": {
      "type": [
        "null",
        "string"
      ]
    },
    "thumbnail": {
      "type": [
        "null",
        "string"
      ]
    },
    "width": {
      "format": "int32",
      "type": [
        "integer",
        "null"
      ]
    }
  },
  "required": [
    "materialId"
  ],
  "title": "GalleryMaterialMetadataCreateParams",
  "type": "object"
}
