{
  "$schema": "https://json-schema.org/draft/2020-12/schema",
  "properties": {
    "appId": {
      "type": "string"
    },
    "appVersion": {
      "type": "string"
    },
    "channel": {
      "type": [
        "null",
        "string"
      ]
    },
    "loadedAt": {
      "type": "string"
    },
    "manifestHash": {
      "type": "string"
    },
    "packageHash": {
      "type": "string"
    },
    "releaseId": {
      "type": [
        "null",
        "string"
      ]
    },
    "signatureRef": {
      "type": [
        "null",
        "string"
      ]
    },
    "sourceKind": {
      "type": "string"
    },
    "sourceUri": {
      "type": "string"
    },
    "tenantEnablementRef": {
      "type": [
        "null",
        "string"
      ]
    },
    "tenantId": {
      "type": [
        "null",
        "string"
      ]
    }
  },
  "required": [
    "appId",
    "appVersion",
    "loadedAt",
    "manifestHash",
    "packageHash",
    "sourceKind",
    "sourceUri"
  ],
  "title": "PluginPackageIdentity",
  "type": "object"
}
